pypoint/__init__.py
pypoint/auth.py
pypoint/const.py
pypoint-3.0.0.dist-info/LICENSE
pypoint-3.0.0.dist-info/METADATA
pypoint-3.0.0.dist-info/WHEEL
pypoint-3.0.0.dist-info/top_level.txt
pypoint-3.0.0.dist-info/RECORD
