Metadata-Version: 2.1
Name: pypoint
Version: 3.0.0
Summary: API for Minut Point
Home-page: https://github.com/fredrike/pypoint
Author: Fredrik Erlandsson
Author-email: fredrik.e@gmail.com
Classifier: Programming Language :: Python :: 3
Classifier: License :: OSI Approved :: MIT License
Classifier: Operating System :: OS Independent
License-File: LICENSE
